{"name":"JavaDoc","scopes":["text.html.javadoc","punctuation.definition.comment.javadoc","comment.block.documentation.javadoc","punctuation.definition.comment.begin.javadoc","punctuation.definition.comment.javadoc","meta.block-tag.javadoc","keyword.other.documentation.param.javadoc","punctuation.definition.keyword.javadoc","keyword.other.documentation.see.javadoc","punctuation.definition.keyword.javadoc","keyword.other.documentation.throws.javadoc","punctuation.definition.keyword.javadoc","keyword.other.documentation.uses-or-provides.javadoc","punctuation.definition.keyword.javadoc","keyword.other.documentation.javadoc","punctuation.definition.keyword.javadoc","variable.parameter.javadoc","markup.underline.link.javadoc","markup.underline.link.javadoc","markup.underline.link.javadoc","markup.underline.link.javadoc","punctuation.section.inline-tag.end.javadoc","meta.inline-tag.javadoc","punctuation.section.inline-tag.begin.javadoc","keyword.other.documentation.code-or-literal.javadoc","punctuation.definition.keyword.javadoc","meta.inline-tag.javadoc","markup.raw.javadoc","punctuation.section.inline-tag.begin.javadoc","keyword.other.documentation.link.javadoc","punctuation.definition.keyword.javadoc","punctuation.section.inline-tag.begin.javadoc","keyword.other.documentation.value.javadoc","punctuation.definition.keyword.javadoc","punctuation.section.inline-tag.begin.javadoc","keyword.other.documentation.javadoc","punctuation.definition.keyword.javadoc","meta.inline-tag.javadoc","punctuation.section.inline-tag.begin.javadoc","keyword.other.documentation.javadoc","punctuation.definition.keyword.javadoc","punctuation.section.inline-tag.end.javadoc","markup.raw.javadoc","markup.raw.javadoc","markup.raw.javadoc","meta.label.javadoc"],"includes":["inline-formatting","javadoc-inline-tags","scope:text.html.basic","inline-formatting","javadoc-block-tag-base","reference","javadoc-inline-tag-terminator","javadoc-inline-tag-terminator","code-tag-bracket-balancing","javadoc-inline-tag-base","code-tag-bracket-balancing","scope:text.html.basic","reference"],"dependencies":["HTML"],"history":[{"tag":"v3096","scopes":100,"unique scopes":56,"includes":17,"unique includes":4,"patterns":40,"unique patterns":27,"avg. specificity":4.27},{"tag":"v3097","scopes":100,"unique scopes":56,"includes":17,"unique includes":4,"patterns":40,"unique patterns":27,"avg. specificity":4.27},{"tag":"v3098","scopes":100,"unique scopes":56,"includes":17,"unique includes":4,"patterns":40,"unique patterns":27,"avg. specificity":4.27},{"tag":"v3099","scopes":100,"unique scopes":56,"includes":17,"unique includes":4,"patterns":40,"unique patterns":27,"avg. specificity":4.27},{"tag":"v3100","scopes":100,"unique scopes":56,"includes":17,"unique includes":4,"patterns":40,"unique patterns":27,"avg. specificity":4.27},{"tag":"v3101","scopes":100,"unique scopes":56,"includes":17,"unique includes":4,"patterns":40,"unique patterns":27,"avg. specificity":4.27},{"tag":"v3102","scopes":100,"unique scopes":56,"includes":17,"unique includes":4,"patterns":40,"unique patterns":27,"avg. specificity":4.27},{"tag":"v3103","scopes":100,"unique scopes":56,"includes":17,"unique includes":4,"patterns":40,"unique patterns":27,"avg. specificity":4.27},{"tag":"v3104","scopes":100,"unique scopes":56,"includes":17,"unique includes":4,"patterns":40,"unique patterns":27,"avg. specificity":4.27},{"tag":"v3105","scopes":100,"unique scopes":56,"includes":17,"unique includes":4,"patterns":40,"unique patterns":27,"avg. specificity":4.27},{"tag":"v3106","scopes":100,"unique scopes":56,"includes":17,"unique includes":4,"patterns":40,"unique patterns":27,"avg. specificity":4.27},{"tag":"v3107","scopes":100,"unique scopes":56,"includes":17,"unique includes":4,"patterns":40,"unique patterns":27,"avg. specificity":4.27},{"tag":"v3108","scopes":100,"unique scopes":56,"includes":17,"unique includes":4,"patterns":40,"unique patterns":27,"avg. specificity":4.27},{"tag":"v3109","scopes":100,"unique scopes":56,"includes":17,"unique includes":4,"patterns":40,"unique patterns":27,"avg. specificity":4.27},{"tag":"v3110","scopes":100,"unique scopes":56,"includes":17,"unique includes":4,"patterns":40,"unique patterns":27,"avg. specificity":4.27},{"tag":"v3111","scopes":100,"unique scopes":56,"includes":17,"unique includes":4,"patterns":40,"unique patterns":27,"avg. specificity":4.27},{"tag":"v3112","scopes":100,"unique scopes":56,"includes":17,"unique includes":4,"patterns":40,"unique patterns":27,"avg. specificity":4.27},{"tag":"v3113","scopes":100,"unique scopes":56,"includes":17,"unique includes":4,"patterns":40,"unique patterns":27,"avg. specificity":4.27},{"tag":"v3114","scopes":100,"unique scopes":56,"includes":17,"unique includes":4,"patterns":40,"unique patterns":27,"avg. specificity":4.27},{"tag":"v3115","scopes":100,"unique scopes":56,"includes":17,"unique includes":4,"patterns":40,"unique patterns":27,"avg. specificity":4.27},{"tag":"v3116","scopes":100,"unique scopes":56,"includes":17,"unique includes":4,"patterns":40,"unique patterns":27,"avg. specificity":4.27},{"tag":"v3117","scopes":100,"unique scopes":56,"includes":17,"unique includes":4,"patterns":40,"unique patterns":27,"avg. specificity":4.27},{"tag":"v3118","scopes":100,"unique scopes":56,"includes":17,"unique includes":4,"patterns":40,"unique patterns":27,"avg. specificity":4.27},{"tag":"v3119","scopes":100,"unique scopes":56,"includes":17,"unique includes":4,"patterns":40,"unique patterns":27,"avg. specificity":4.27},{"tag":"v3120","scopes":100,"unique scopes":56,"includes":17,"unique includes":4,"patterns":40,"unique patterns":27,"avg. specificity":4.27},{"tag":"v3121","scopes":100,"unique scopes":56,"includes":17,"unique includes":4,"patterns":40,"unique patterns":27,"avg. specificity":4.27},{"tag":"v3122","scopes":100,"unique scopes":56,"includes":17,"unique includes":4,"patterns":40,"unique patterns":27,"avg. specificity":4.27},{"tag":"v3123","scopes":100,"unique scopes":56,"includes":17,"unique includes":4,"patterns":40,"unique patterns":27,"avg. specificity":4.27},{"tag":"v3124","scopes":100,"unique scopes":56,"includes":17,"unique includes":4,"patterns":40,"unique patterns":27,"avg. specificity":4.27},{"tag":"v3125","scopes":100,"unique scopes":56,"includes":17,"unique includes":4,"patterns":40,"unique patterns":27,"avg. specificity":4.27},{"tag":"v3126","scopes":100,"unique scopes":56,"includes":17,"unique includes":4,"patterns":40,"unique patterns":27,"avg. specificity":4.27},{"tag":"v3127","scopes":100,"unique scopes":56,"includes":17,"unique includes":4,"patterns":40,"unique patterns":27,"avg. specificity":4.27},{"tag":"v3128","scopes":100,"unique scopes":56,"includes":17,"unique includes":4,"patterns":40,"unique patterns":27,"avg. specificity":4.27},{"tag":"v3129","scopes":100,"unique scopes":56,"includes":17,"unique includes":4,"patterns":40,"unique patterns":27,"avg. specificity":4.27},{"tag":"v3130","scopes":100,"unique scopes":56,"includes":17,"unique includes":4,"patterns":40,"unique patterns":27,"avg. specificity":4.27},{"tag":"v3131","scopes":100,"unique scopes":56,"includes":17,"unique includes":4,"patterns":40,"unique patterns":27,"avg. specificity":4.27},{"tag":"v3132","scopes":100,"unique scopes":56,"includes":17,"unique includes":4,"patterns":40,"unique patterns":27,"avg. specificity":4.27},{"tag":"v3133","scopes":100,"unique scopes":56,"includes":17,"unique includes":4,"patterns":40,"unique patterns":27,"avg. specificity":4.27},{"tag":"v3134","scopes":100,"unique scopes":56,"includes":17,"unique includes":4,"patterns":40,"unique patterns":27,"avg. specificity":4.27},{"tag":"v3135","scopes":100,"unique scopes":56,"includes":17,"unique includes":4,"patterns":40,"unique patterns":27,"avg. specificity":4.27},{"tag":"v3136","scopes":100,"unique scopes":56,"includes":17,"unique includes":4,"patterns":40,"unique patterns":27,"avg. specificity":4.27},{"tag":"v3137","scopes":100,"unique scopes":56,"includes":17,"unique includes":4,"patterns":40,"unique patterns":27,"avg. specificity":4.27},{"tag":"v3138","scopes":100,"unique scopes":56,"includes":17,"unique includes":4,"patterns":40,"unique patterns":27,"avg. specificity":4.27},{"tag":"v3140","scopes":100,"unique scopes":56,"includes":17,"unique includes":4,"patterns":40,"unique patterns":27,"avg. specificity":4.27},{"tag":"v3141","scopes":100,"unique scopes":56,"includes":17,"unique includes":4,"patterns":40,"unique patterns":27,"avg. specificity":4.27},{"tag":"v3142","scopes":100,"unique scopes":56,"includes":17,"unique includes":4,"patterns":40,"unique patterns":27,"avg. specificity":4.27},{"tag":"v3143","scopes":100,"unique scopes":56,"includes":17,"unique includes":4,"patterns":40,"unique patterns":27,"avg. specificity":4.27},{"tag":"v3144","scopes":100,"unique scopes":56,"includes":17,"unique includes":4,"patterns":40,"unique patterns":27,"avg. specificity":4.27},{"tag":"v3145","scopes":100,"unique scopes":56,"includes":17,"unique includes":4,"patterns":40,"unique patterns":27,"avg. specificity":4.27},{"tag":"v3146","scopes":100,"unique scopes":56,"includes":17,"unique includes":4,"patterns":40,"unique patterns":27,"avg. specificity":4.27},{"tag":"v3147","scopes":100,"unique scopes":56,"includes":17,"unique includes":4,"patterns":40,"unique patterns":27,"avg. specificity":4.27},{"tag":"v3148","scopes":100,"unique scopes":56,"includes":17,"unique includes":4,"patterns":40,"unique patterns":27,"avg. specificity":4.27},{"tag":"v3149","scopes":100,"unique scopes":56,"includes":17,"unique includes":4,"patterns":40,"unique patterns":27,"avg. specificity":4.27},{"tag":"v3150","scopes":100,"unique scopes":56,"includes":17,"unique includes":4,"patterns":40,"unique patterns":27,"avg. specificity":4.27},{"tag":"v3151","scopes":100,"unique scopes":56,"includes":17,"unique includes":4,"patterns":40,"unique patterns":27,"avg. specificity":4.27},{"tag":"v3152","scopes":100,"unique scopes":56,"includes":17,"unique includes":4,"patterns":40,"unique patterns":27,"avg. specificity":4.27},{"tag":"v3153","scopes":100,"unique scopes":56,"includes":17,"unique includes":4,"patterns":40,"unique patterns":27,"avg. specificity":4.27},{"tag":"v3154","scopes":100,"unique scopes":56,"includes":17,"unique includes":4,"patterns":40,"unique patterns":27,"avg. specificity":4.27},{"tag":"v3155","scopes":100,"unique scopes":56,"includes":17,"unique includes":4,"patterns":40,"unique patterns":27,"avg. specificity":4.27},{"tag":"v3156","scopes":100,"unique scopes":56,"includes":17,"unique includes":4,"patterns":40,"unique patterns":27,"avg. specificity":4.27},{"tag":"v3157","scopes":46,"unique scopes":21,"includes":17,"unique includes":10,"patterns":32,"unique patterns":28,"avg. specificity":4.086956521739131},{"tag":"v3158","scopes":46,"unique scopes":21,"includes":17,"unique includes":10,"patterns":32,"unique patterns":28,"avg. specificity":4.086956521739131},{"tag":"v3159","scopes":46,"unique scopes":21,"includes":17,"unique includes":10,"patterns":32,"unique patterns":28,"avg. specificity":4.086956521739131},{"tag":"v3160","scopes":46,"unique scopes":21,"includes":17,"unique includes":10,"patterns":32,"unique patterns":28,"avg. specificity":4.086956521739131},{"tag":"v3161","scopes":46,"unique scopes":21,"includes":17,"unique includes":10,"patterns":32,"unique patterns":28,"avg. specificity":4.086956521739131},{"tag":"v3162","scopes":46,"unique scopes":21,"includes":17,"unique includes":10,"patterns":32,"unique patterns":28,"avg. specificity":4.086956521739131},{"tag":"v3163","scopes":46,"unique scopes":21,"includes":17,"unique includes":10,"patterns":32,"unique patterns":28,"avg. specificity":4.086956521739131},{"tag":"v3164","scopes":46,"unique scopes":21,"includes":17,"unique includes":10,"patterns":32,"unique patterns":28,"avg. specificity":4.086956521739131},{"tag":"v3165","scopes":46,"unique scopes":21,"includes":17,"unique includes":10,"patterns":32,"unique patterns":28,"avg. specificity":4.086956521739131},{"tag":"v3166","scopes":46,"unique scopes":21,"includes":17,"unique includes":10,"patterns":32,"unique patterns":28,"avg. specificity":4.086956521739131},{"tag":"v3167","scopes":46,"unique scopes":21,"includes":17,"unique includes":10,"patterns":32,"unique patterns":28,"avg. specificity":4.086956521739131},{"tag":"v3168","scopes":46,"unique scopes":21,"includes":17,"unique includes":10,"patterns":32,"unique patterns":28,"avg. specificity":4.086956521739131},{"tag":"v3169","scopes":46,"unique scopes":21,"includes":17,"unique includes":10,"patterns":32,"unique patterns":28,"avg. specificity":4.086956521739131},{"tag":"v3170","scopes":46,"unique scopes":21,"includes":17,"unique includes":10,"patterns":32,"unique patterns":28,"avg. specificity":4.086956521739131},{"tag":"v3171","scopes":46,"unique scopes":21,"includes":17,"unique includes":10,"patterns":32,"unique patterns":28,"avg. specificity":4.086956521739131},{"tag":"v3172","scopes":46,"unique scopes":21,"includes":17,"unique includes":10,"patterns":32,"unique patterns":28,"avg. specificity":4.086956521739131},{"tag":"v3173","scopes":46,"unique scopes":21,"includes":17,"unique includes":10,"patterns":32,"unique patterns":28,"avg. specificity":4.086956521739131},{"tag":"v3174","scopes":46,"unique scopes":21,"includes":17,"unique includes":10,"patterns":32,"unique patterns":28,"avg. specificity":4.086956521739131},{"tag":"v3175","scopes":46,"unique scopes":21,"includes":17,"unique includes":10,"patterns":32,"unique patterns":28,"avg. specificity":4.086956521739131},{"tag":"v3176","scopes":46,"unique scopes":21,"includes":17,"unique includes":10,"patterns":32,"unique patterns":28,"avg. specificity":4.086956521739131},{"tag":"v3179","scopes":46,"unique scopes":21,"includes":17,"unique includes":10,"patterns":32,"unique patterns":28,"avg. specificity":4.086956521739131},{"tag":"v3180","scopes":46,"unique scopes":21,"includes":17,"unique includes":10,"patterns":32,"unique patterns":28,"avg. specificity":4.086956521739131},{"tag":"v3181","scopes":46,"unique scopes":21,"includes":13,"unique includes":8,"patterns":31,"unique patterns":27,"avg. specificity":4.086956521739131},{"tag":"v3182","scopes":46,"unique scopes":21,"includes":13,"unique includes":8,"patterns":31,"unique patterns":27,"avg. specificity":4.086956521739131},{"tag":"v3183","scopes":46,"unique scopes":21,"includes":13,"unique includes":8,"patterns":31,"unique patterns":27,"avg. specificity":4.086956521739131},{"tag":"v3184","scopes":46,"unique scopes":21,"includes":13,"unique includes":8,"patterns":31,"unique patterns":27,"avg. specificity":4.086956521739131},{"tag":"v3186","scopes":46,"unique scopes":21,"includes":13,"unique includes":8,"patterns":31,"unique patterns":27,"avg. specificity":4.086956521739131},{"tag":"v3187","scopes":46,"unique scopes":21,"includes":13,"unique includes":8,"patterns":31,"unique patterns":27,"avg. specificity":4.086956521739131},{"tag":"v3188","scopes":46,"unique scopes":21,"includes":13,"unique includes":8,"patterns":31,"unique patterns":27,"avg. specificity":4.086956521739131},{"tag":"v3189","scopes":46,"unique scopes":21,"includes":13,"unique includes":8,"patterns":31,"unique patterns":27,"avg. specificity":4.086956521739131},{"tag":"master","scopes":46,"unique scopes":21,"includes":13,"unique includes":8,"patterns":31,"unique patterns":27,"avg. specificity":4.086956521739131}]}