{"name":"BibTeX","scopes":["text.bibtex","punctuation.definition.comment.bibtex","comment.line.at-sign.bibtex","keyword.other.string-constant.bibtex","punctuation.definition.keyword.bibtex","punctuation.section.string-constant.begin.bibtex","variable.other.bibtex","meta.string-constant.braces.bibtex","punctuation.section.string-constant.end.bibtex","keyword.other.string-constant.bibtex","punctuation.definition.keyword.bibtex","punctuation.section.string-constant.begin.bibtex","variable.other.bibtex","meta.string-constant.parenthesis.bibtex","punctuation.section.string-constant.end.bibtex","keyword.other.entry-type.bibtex","punctuation.definition.keyword.bibtex","punctuation.section.entry.begin.bibtex","entity.name.type.entry-key.bibtex","meta.entry.braces.bibtex","punctuation.section.entry.end.bibtex","string.unquoted.key.bibtex","punctuation.separator.key-value.bibtex","meta.key-assignment.bibtex","keyword.other.entry-type.bibtex","punctuation.definition.keyword.bibtex","punctuation.section.entry.begin.bibtex","entity.name.type.entry-key.bibtex","meta.entry.parenthesis.bibtex","punctuation.section.entry.end.bibtex","string.unquoted.key.bibtex","punctuation.separator.key-value.bibtex","meta.key-assignment.bibtex","comment.block.bibtex","constant.numeric.bibtex","punctuation.definition.group.begin.bibtex","punctuation.definition.group.end.bibtex","punctuation.definition.string.begin.bibtex","string.quoted.double.bibtex","punctuation.definition.string.end.bibtex","punctuation.definition.string.begin.bibtex","string.quoted.other.braces.bibtex","punctuation.definition.string.end.bibtex","invalid.illegal.at-sign.bibtex"],"includes":["string_content","string_content","string_content","integer","string_content","integer","nested_braces","nested_braces","nested_braces"],"dependencies":[],"history":[{"tag":"v3096","scopes":44,"unique scopes":28,"includes":9,"unique includes":3,"avg. specificity":4},{"tag":"v3097","scopes":44,"unique scopes":28,"includes":9,"unique includes":3,"avg. specificity":4},{"tag":"v3098","scopes":44,"unique scopes":28,"includes":9,"unique includes":3,"avg. specificity":4},{"tag":"v3099","scopes":44,"unique scopes":28,"includes":9,"unique includes":3,"avg. specificity":4},{"tag":"v3100","scopes":44,"unique scopes":28,"includes":9,"unique includes":3,"avg. specificity":4},{"tag":"v3101","scopes":44,"unique scopes":28,"includes":9,"unique includes":3,"avg. specificity":4},{"tag":"v3102","scopes":44,"unique scopes":28,"includes":9,"unique includes":3,"avg. specificity":4},{"tag":"v3103","scopes":44,"unique scopes":28,"includes":9,"unique includes":3,"avg. specificity":4},{"tag":"v3104","scopes":44,"unique scopes":28,"includes":9,"unique includes":3,"avg. specificity":4},{"tag":"v3105","scopes":44,"unique scopes":28,"includes":9,"unique includes":3,"avg. specificity":4},{"tag":"v3106","scopes":44,"unique scopes":28,"includes":9,"unique includes":3,"avg. specificity":4},{"tag":"v3107","scopes":44,"unique scopes":28,"includes":9,"unique includes":3,"avg. specificity":4},{"tag":"v3108","scopes":44,"unique scopes":28,"includes":9,"unique includes":3,"avg. specificity":4},{"tag":"v3109","scopes":44,"unique scopes":28,"includes":9,"unique includes":3,"avg. specificity":4},{"tag":"v3110","scopes":44,"unique scopes":28,"includes":9,"unique includes":3,"avg. specificity":4},{"tag":"v3111","scopes":44,"unique scopes":28,"includes":9,"unique includes":3,"avg. specificity":4},{"tag":"v3112","scopes":44,"unique scopes":28,"includes":9,"unique includes":3,"avg. specificity":4},{"tag":"v3113","scopes":44,"unique scopes":28,"includes":9,"unique includes":3,"avg. specificity":4},{"tag":"v3114","scopes":44,"unique scopes":28,"includes":9,"unique includes":3,"avg. specificity":4},{"tag":"master","scopes":44,"unique scopes":28,"includes":9,"unique includes":3,"avg. specificity":4}]}